MANIFEST.in
README.rst
requirements.txt
setup.cfg
setup.py
sphinx_bulma_theme/__init__.py
sphinx_bulma_theme/body.html
sphinx_bulma_theme/fs.py
sphinx_bulma_theme/generate-sass.py
sphinx_bulma_theme/genindex.html
sphinx_bulma_theme/head.html
sphinx_bulma_theme/layout.html
sphinx_bulma_theme/page.html
sphinx_bulma_theme/search.html
sphinx_bulma_theme/searchbox.html
sphinx_bulma_theme/sphinx-bulma.src.js
sphinx_bulma_theme/theme.conf
sphinx_bulma_theme/version.py
sphinx_bulma_theme.egg-info/PKG-INFO
sphinx_bulma_theme.egg-info/SOURCES.txt
sphinx_bulma_theme.egg-info/dependency_links.txt
sphinx_bulma_theme.egg-info/entry_points.txt
sphinx_bulma_theme.egg-info/not-zip-safe
sphinx_bulma_theme.egg-info/requires.txt
sphinx_bulma_theme.egg-info/top_level.txt
sphinx_bulma_theme/components/breadcrumbs.html
sphinx_bulma_theme/components/footer.html
sphinx_bulma_theme/components/sidebar.html
sphinx_bulma_theme/components/topbar.html
sphinx_bulma_theme/example/__init__.py
sphinx_bulma_theme/static/css/theme.css
sphinx_bulma_theme/static/fonts/AnonymousPro-Bold.ttf
sphinx_bulma_theme/static/fonts/AnonymousPro-BoldItalic.ttf
sphinx_bulma_theme/static/fonts/AnonymousPro-Italic.ttf
sphinx_bulma_theme/static/fonts/AnonymousPro-Regular.ttf
sphinx_bulma_theme/static/fonts/Inconsolata-Bold.ttf
sphinx_bulma_theme/static/fonts/Inconsolata-Regular.ttf
sphinx_bulma_theme/static/fonts/Lato-Bold.ttf
sphinx_bulma_theme/static/fonts/Lato-Regular.ttf
sphinx_bulma_theme/static/fonts/PT_Sans-Web-Bold.ttf
sphinx_bulma_theme/static/fonts/PT_Sans-Web-BoldItalic.ttf
sphinx_bulma_theme/static/fonts/PT_Sans-Web-Italic.ttf
sphinx_bulma_theme/static/fonts/PT_Sans-Web-Regular.ttf
sphinx_bulma_theme/static/fonts/RobotoSlab-Bold.ttf
sphinx_bulma_theme/static/fonts/RobotoSlab-Regular.ttf
sphinx_bulma_theme/static/fonts/fontawesome-webfont.eot
sphinx_bulma_theme/static/fonts/fontawesome-webfont.svg
sphinx_bulma_theme/static/fonts/fontawesome-webfont.ttf
sphinx_bulma_theme/static/fonts/fontawesome-webfont.woff
sphinx_bulma_theme/static/js/theme.js